serply/__init__.py
serply/consts.py
serply/serply.py
serply-0.1.3.dist-info/METADATA
serply-0.1.3.dist-info/WHEEL
serply-0.1.3.dist-info/RECORD
