Metadata-Version: 2.1
Name: serply
Version: 0.1.3
Summary: 
Author: Tuan Nguyen
Author-email: tuan@tuangeek.com
Requires-Python: >=3.7,<4.0
Classifier: Programming Language :: Python :: 3
Classifier: Programming Language :: Python :: 3.7
Classifier: Programming Language :: Python :: 3.8
Classifier: Programming Language :: Python :: 3.9
Classifier: Programming Language :: Python :: 3.10
Classifier: Programming Language :: Python :: 3.11
Classifier: Programming Language :: Python :: 3.12
Requires-Dist: aiohttp (>=3.8.4,<4.0.0)
Requires-Dist: requests (>=2.28.2,<3.0.0)
